Andreani_QA_Jmeter/Jmeter.py
Andreani_QA_Jmeter/__init__.py
Andreani_QA_Jmeter-0.0.2.dist-info/METADATA
Andreani_QA_Jmeter-0.0.2.dist-info/WHEEL
Andreani_QA_Jmeter-0.0.2.dist-info/top_level.txt
Andreani_QA_Jmeter-0.0.2.dist-info/RECORD
