Metadata-Version: 2.1
Name: Andreani_QA_Jmeter
Version: 0.0.2
Summary: SeleniumFramework para ejecución de casos automatizados
Home-page: UNKNOWN
Author: AndreaniTesting
Author-email: user_appglatest@andreani.com
License: MIT
Platform: UNKNOWN
